pyDANT/AutoCuration.py
pyDANT/ComputeWaveformFeatures.py
pyDANT/IterativeClustering.py
pyDANT/MotionEstimation.py
pyDANT/Preprocess.py
pyDANT/__init__.py
pyDANT/utils.py
pydant-1.0.1.dist-info/licenses/LICENSE
pydant-1.0.1.dist-info/METADATA
pydant-1.0.1.dist-info/WHEEL
pydant-1.0.1.dist-info/top_level.txt
pydant-1.0.1.dist-info/RECORD
