Metadata-Version: 2.4
Name: pyDANT
Version: 1.0.1
Summary: A Python package for tracking neurons across days
Home-page: https://github.com/jiumao2/pyDANT
Author: Yue Huang
Author-email: yue_huang@pku.edu.cn
Classifier: Intended Audience :: Science/Research
Classifier: License :: OSI Approved :: GNU General Public License v3 (GPLv3)
Classifier: Programming Language :: Python :: 3
Requires-Python: >=3.9
License-File: LICENSE
Requires-Dist: hdbscan
Requires-Dist: scikit-learn
Requires-Dist: ipykernel
Requires-Dist: tqdm
Requires-Dist: h5py
Requires-Dist: matplotlib
Requires-Dist: hjson
Dynamic: author
Dynamic: author-email
Dynamic: classifier
Dynamic: description
Dynamic: description-content-type
Dynamic: home-page
Dynamic: license-file
Dynamic: requires-dist
Dynamic: requires-python
Dynamic: summary
